densitypdf/__init__.py
densitypdf/builtin/builtindensitypdf.py
densitypdf/builtin/scipyreplacements.py
densitypdf-0.1.4.dist-info/licenses/LICENSE
densitypdf-0.1.4.dist-info/METADATA
densitypdf-0.1.4.dist-info/WHEEL
densitypdf-0.1.4.dist-info/entry_points.txt
densitypdf-0.1.4.dist-info/top_level.txt
densitypdf-0.1.4.dist-info/RECORD
